Metadata-Version: 2.1
Name: online-store-vtcu
Version: 0.1.2
Summary: Исполняемый пакет для управления пользователями и заказами в онлайн-магазине
Author-email: vtcu <sleeve_thinker_0d@icloud.com>
License: MIT
Classifier: Programming Language :: Python :: 3
Classifier: License :: OSI Approved :: MIT License
Classifier: Operating System :: OS Independent
Requires-Python: >=3.8
Provides-Extra: dev
Requires-Dist: pytest>=6.2.1; extra == "dev"
Requires-Dist: flake8>=3.8.4; extra == "dev"
